<?xml version="1.0" encoding="utf-8"?>
<edits file="0155">
  <edit end="234" file="0155" index="0001" part="1" start="232" type="RT">
    <original>of</original>
    <corrections>
      <correction>for</correction>
    </corrections>
  </edit>
  <edit end="317" file="0155" index="0002" part="1" start="315" type="RT">
    <original>of</original>
    <corrections>
      <correction>for</correction>
    </corrections>
  </edit>
  <edit end="226" file="0155" index="0003" part="2" start="224" type="RT">
    <original>in</original>
    <corrections>
      <correction>at</correction>
    </corrections>
  </edit>
  <edit end="231" file="0155" index="0004" part="2" start="227" type="UD">
    <original>the </original>
    <corrections>
      <correction>
        <empty/>
      </correction>
    </corrections>
  </edit>
  <edit end="300" file="0155" index="0005" part="2" start="297" type="RT">
    <original>for</original>
    <corrections>
      <correction>on</correction>
    </corrections>
  </edit>
  <edit end="354" file="0155" index="0006" part="2" start="352" type="RT">
    <original>in</original>
    <corrections>
      <correction>at</correction>
    </corrections>
  </edit>
</edits>
