<?xml version="1.0" encoding="utf-8"?>
<edits file="0286">
  <edit end="329" file="0286" index="0001" part="1" start="329" type="MT">
    <original>
      <empty/>
    </original>
    <corrections>
      <correction>of </correction>
    </corrections>
  </edit>
  <edit end="570" file="0286" index="0002" part="1" start="570" type="MD">
    <original>
      <empty/>
    </original>
    <corrections>
      <correction>a </correction>
    </corrections>
  </edit>
  <edit end="733" file="0286" index="0003" part="1" start="733" type="MD">
    <original>
      <empty/>
    </original>
    <corrections>
      <correction>a </correction>
    </corrections>
  </edit>
  <edit end="14" file="0286" index="0004" part="3" start="11" type="UT">
    <original>at </original>
    <corrections>
      <correction>
        <empty/>
      </correction>
    </corrections>
  </edit>
  <edit end="72" file="0286" index="0005" part="3" start="68" type="UD">
    <original>the </original>
    <corrections>
      <correction>
        <empty/>
      </correction>
    </corrections>
  </edit>
  <edit end="788" file="0286" index="0006" part="3" start="785" type="RT">
    <original>for</original>
    <corrections>
      <correction>to</correction>
    </corrections>
  </edit>
</edits>
