<?xml version="1.0" encoding="utf-8"?>
<edits file="0452">
  <edit end="236" file="0452" index="0001" part="1" start="234" type="RT">
    <original>on</original>
    <corrections>
      <correction>at</correction>
    </corrections>
  </edit>
  <edit end="291" file="0452" index="0002" part="1" start="291" type="MD">
    <original>
      <empty/>
    </original>
    <corrections>
      <correction>the </correction>
    </corrections>
  </edit>
  <edit end="472" file="0452" index="0003" part="1" start="472" type="MD">
    <original>
      <empty/>
    </original>
    <corrections>
      <correction>the </correction>
    </corrections>
  </edit>
  <edit end="532" file="0452" index="0004" part="1" start="532" type="MD">
    <original>
      <empty/>
    </original>
    <corrections>
      <correction>the </correction>
    </corrections>
  </edit>
  <edit end="656" file="0452" index="0005" part="1" start="654" type="UD">
    <original>a </original>
    <corrections>
      <correction>
        <empty/>
      </correction>
    </corrections>
  </edit>
  <edit end="673" file="0452" index="0006" part="1" start="671" type="RT">
    <original>in</original>
    <corrections>
      <correction>of</correction>
    </corrections>
  </edit>
  <edit end="729" file="0452" index="0007" part="1" start="726" type="UT">
    <original>in </original>
    <corrections>
      <correction>
        <empty/>
      </correction>
    </corrections>
  </edit>
  <edit end="773" file="0452" index="0008" part="1" start="771" type="RT">
    <original>of</original>
    <corrections>
      <correction>about</correction>
    </corrections>
  </edit>
  <edit end="121" file="0452" index="0009" part="4" start="120" type="RD">
    <original>a</original>
    <corrections>
      <correction>the</correction>
    </corrections>
  </edit>
  <edit end="189" file="0452" index="0010" part="4" start="189" type="MD">
    <original>
      <empty/>
    </original>
    <corrections>
      <correction>the </correction>
    </corrections>
  </edit>
  <edit end="206" file="0452" index="0011" part="4" start="204" type="RT">
    <original>on</original>
    <corrections>
      <correction>at</correction>
    </corrections>
  </edit>
  <edit end="563" file="0452" index="0012" part="4" start="563" type="MD">
    <original>
      <empty/>
    </original>
    <corrections>
      <correction>the </correction>
    </corrections>
  </edit>
  <edit end="686" file="0452" index="0013" part="4" start="683" type="UT">
    <original>of </original>
    <corrections>
      <correction>
        <empty/>
      </correction>
    </corrections>
  </edit>
</edits>
