<?xml version="1.0" encoding="utf-8"?>
<edits file="0468">
  <edit end="96" file="0468" index="0001" part="1" start="94" type="RT">
    <original>on</original>
    <corrections>
      <correction>in</correction>
    </corrections>
  </edit>
  <edit end="210" file="0468" index="0002" part="1" start="210" type="MT">
    <original>
      <empty/>
    </original>
    <corrections>
      <correction>at </correction>
    </corrections>
  </edit>
  <edit end="499" file="0468" index="0003" part="1" start="495" type="UD">
    <original>the </original>
    <corrections>
      <correction>
        <empty/>
      </correction>
    </corrections>
  </edit>
  <edit end="783" file="0468" index="0004" part="1" start="783" type="MT">
    <original>
      <empty/>
    </original>
    <corrections>
      <correction>to </correction>
    </corrections>
  </edit>
  <edit end="70" file="0468" index="0005" part="3" start="70" type="MT">
    <original>
      <empty/>
    </original>
    <corrections>
      <correction>from </correction>
    </corrections>
  </edit>
</edits>
