<?xml version="1.0" encoding="utf-8"?>
<edits file="0862">
  <edit end="404" file="0862" index="0001" part="1" start="404" type="MD">
    <original>
      <empty/>
    </original>
    <corrections>
      <correction>an </correction>
    </corrections>
  </edit>
  <edit end="341" file="0862" index="0002" part="2" start="337" type="UD">
    <original>the </original>
    <corrections>
      <correction>
        <empty/>
      </correction>
    </corrections>
  </edit>
  <edit end="465" file="0862" index="0003" part="2" start="464" type="RD">
    <original>A</original>
    <corrections>
      <correction>The</correction>
    </corrections>
  </edit>
</edits>
