<?xml version="1.0" encoding="utf-8"?>
<edits file="1787">
  <edit end="199" file="1787" index="0001" part="1" start="199" type="MD">
    <original>
      <empty/>
    </original>
    <corrections>
      <correction>the </correction>
    </corrections>
  </edit>
  <edit end="480" file="1787" index="0002" part="1" start="480" type="MD">
    <original>
      <empty/>
    </original>
    <corrections>
      <correction>the </correction>
    </corrections>
  </edit>
  <edit end="559" file="1787" index="0003" part="1" start="559" type="MD">
    <original>
      <empty/>
    </original>
    <corrections>
      <correction>their </correction>
    </corrections>
  </edit>
  <edit end="668" file="1787" index="0004" part="1" start="668" type="MD">
    <original>
      <empty/>
    </original>
    <corrections>
      <correction>a </correction>
    </corrections>
  </edit>
  <edit end="41" file="1787" index="0005" part="4" start="41" type="MD">
    <original>
      <empty/>
    </original>
    <corrections>
      <correction>the </correction>
    </corrections>
  </edit>
  <edit end="109" file="1787" index="0006" part="4" start="103" type="UT">
    <original>about </original>
    <corrections>
      <correction>
        <empty/>
      </correction>
    </corrections>
  </edit>
  <edit end="616" file="1787" index="0007" part="4" start="616" type="MD">
    <original>
      <empty/>
    </original>
    <corrections>
      <correction>a </correction>
    </corrections>
  </edit>
</edits>
